reedautomated/__init__.py
reedautomated/chromesettings.py
reedautomated/firstwebpage.py
reedautomated/inputs.py
reedautomated/login.py
reedautomated/main.py
reedautomated/reedautoassistant.py
reedautomated-0.5.1.dist-info/METADATA
reedautomated-0.5.1.dist-info/WHEEL
reedautomated-0.5.1.dist-info/top_level.txt
reedautomated-0.5.1.dist-info/RECORD
