Metadata-Version: 2.4
Name: reedautomated
Version: 0.5.1
Requires-Dist: selenium
Requires-Dist: schedule
Requires-Dist: chromedriver
Dynamic: requires-dist
